Topsis/__init__.py
Topsis/__main__.py
Topsis_Raghav_102103042-1.1.2.dist-info/METADATA
Topsis_Raghav_102103042-1.1.2.dist-info/WHEEL
Topsis_Raghav_102103042-1.1.2.dist-info/entry_points.txt
Topsis_Raghav_102103042-1.1.2.dist-info/top_level.txt
Topsis_Raghav_102103042-1.1.2.dist-info/RECORD
